{
    "name": "All Requests",
    "numberOfRequests": {
        "total": 1000,
        "ok": 785,
        "ko": 215
    },
    "minResponseTime": {
        "total": 9,
        "ok": 4048,
        "ko": 9
    },
    "maxResponseTime": {
        "total": 19409,
        "ok": 19409,
        "ko": 43
    },
    "meanResponseTime": {
        "total": 12232,
        "ok": 15579,
        "ko": 12
    },
    "standardDeviation": {
        "total": 7393,
        "ok": 4185,
        "ko": 3
    },
    "percentiles1": {
        "total": 16849,
        "ok": 17984,
        "ko": 12
    },
    "percentiles2": {
        "total": 18266,
        "ok": 18354,
        "ko": 12
    },
    "percentiles3": {
        "total": 18932,
        "ok": 18983,
        "ko": 15
    },
    "percentiles4": {
        "total": 19142,
        "ok": 19166,
        "ko": 19
    },
    "group1": {
    "name": "t < 800 ms",
    "htmlName": "t < 800 ms",
    "count": 0,
    "percentage": 0
},
    "group2": {
    "name": "800 ms <= t < 1200 ms",
    "htmlName": "t >= 800 ms <br> t < 1200 ms",
    "count": 0,
    "percentage": 0
},
    "group3": {
    "name": "t >= 1200 ms",
    "htmlName": "t >= 1200 ms",
    "count": 785,
    "percentage": 79
},
    "group4": {
    "name": "failed",
    "htmlName": "failed",
    "count": 215,
    "percentage": 22
},
    "meanNumberOfRequestsPerSecond": {
        "total": 8.474576271186441,
        "ok": 6.6525423728813555,
        "ko": 1.8220338983050848
    }
}