{
  "type": "GROUP",
"name": "All Requests",
"path": "",
"pathFormatted": "group_missing-name--1146707516",
"stats": {
    "name": "All Requests",
    "numberOfRequests": {
        "total": 5000,
        "ok": 527,
        "ko": 4473
    },
    "minResponseTime": {
        "total": 88,
        "ok": 88,
        "ko": 60000
    },
    "maxResponseTime": {
        "total": 60011,
        "ok": 59801,
        "ko": 60011
    },
    "meanResponseTime": {
        "total": 56554,
        "ok": 27306,
        "ko": 60000
    },
    "standardDeviation": {
        "total": 11461,
        "ok": 17028,
        "ko": 0
    },
    "percentiles1": {
        "total": 60000,
        "ok": 25669,
        "ko": 60000
    },
    "percentiles2": {
        "total": 60000,
        "ok": 42894,
        "ko": 60000
    },
    "percentiles3": {
        "total": 60001,
        "ok": 54480,
        "ko": 60001
    },
    "percentiles4": {
        "total": 60001,
        "ok": 57315,
        "ko": 60001
    },
    "group1": {
    "name": "t < 800 ms",
    "htmlName": "t < 800 ms",
    "count": 6,
    "percentage": 0
},
    "group2": {
    "name": "800 ms <= t < 1200 ms",
    "htmlName": "t >= 800 ms <br> t < 1200 ms",
    "count": 4,
    "percentage": 0
},
    "group3": {
    "name": "t >= 1200 ms",
    "htmlName": "t >= 1200 ms",
    "count": 517,
    "percentage": 10
},
    "group4": {
    "name": "failed",
    "htmlName": "failed",
    "count": 4473,
    "percentage": 89
},
    "meanNumberOfRequestsPerSecond": {
        "total": 31.25,
        "ok": 3.29375,
        "ko": 27.95625
    }
},
"contents": {
"req_postrequest--996301393": {
        "type": "REQUEST",
        "name": "PostRequest",
"path": "PostRequest",
"pathFormatted": "req_postrequest--996301393",
"stats": {
    "name": "PostRequest",
    "numberOfRequests": {
        "total": 5000,
        "ok": 527,
        "ko": 4473
    },
    "minResponseTime": {
        "total": 88,
        "ok": 88,
        "ko": 60000
    },
    "maxResponseTime": {
        "total": 60011,
        "ok": 59801,
        "ko": 60011
    },
    "meanResponseTime": {
        "total": 56554,
        "ok": 27306,
        "ko": 60000
    },
    "standardDeviation": {
        "total": 11461,
        "ok": 17028,
        "ko": 0
    },
    "percentiles1": {
        "total": 60000,
        "ok": 25669,
        "ko": 60000
    },
    "percentiles2": {
        "total": 60000,
        "ok": 42894,
        "ko": 60000
    },
    "percentiles3": {
        "total": 60001,
        "ok": 54480,
        "ko": 60001
    },
    "percentiles4": {
        "total": 60001,
        "ok": 57315,
        "ko": 60001
    },
    "group1": {
    "name": "t < 800 ms",
    "htmlName": "t < 800 ms",
    "count": 6,
    "percentage": 0
},
    "group2": {
    "name": "800 ms <= t < 1200 ms",
    "htmlName": "t >= 800 ms <br> t < 1200 ms",
    "count": 4,
    "percentage": 0
},
    "group3": {
    "name": "t >= 1200 ms",
    "htmlName": "t >= 1200 ms",
    "count": 517,
    "percentage": 10
},
    "group4": {
    "name": "failed",
    "htmlName": "failed",
    "count": 4473,
    "percentage": 89
},
    "meanNumberOfRequestsPerSecond": {
        "total": 31.25,
        "ok": 3.29375,
        "ko": 27.95625
    }
}
    }
}

}